setup.py
src/CDHTMLTable/__init__.py
src/CDHTMLTable/cell.py
src/CDHTMLTable/column.py
src/CDHTMLTable/common.py
src/CDHTMLTable/row.py
src/CDHTMLTable/table.py
src/CDHTMLTable.egg-info/PKG-INFO
src/CDHTMLTable.egg-info/SOURCES.txt
src/CDHTMLTable.egg-info/dependency_links.txt
src/CDHTMLTable.egg-info/top_level.txt